LICENSE
MANIFEST.in
README.md
setup.cfg
setup.py
sqlite/init.h
sqlite/shell.c
sqlite/sqlite3-arabic-tokenizer.c
sqlite/sqlite3-arabic-tokenizer.h
sqlite/sqlite3.c
sqlite/sqlite3.h
sqlite/sqlite3ext.h
sqlite/test_windirent.h
sqlite3_arabic_tokenizer/__init__.py
sqlite3_arabic_tokenizer/dbapi2.py
sqlite3_arabic_tokenizer.egg-info/PKG-INFO
sqlite3_arabic_tokenizer.egg-info/SOURCES.txt
sqlite3_arabic_tokenizer.egg-info/dependency_links.txt
sqlite3_arabic_tokenizer.egg-info/top_level.txt
src/arabic_tokenizer.c
src/arabic_tokenizer.h
src/blob.c
src/blob.h
src/cache.c
src/cache.h
src/connection.c
src/connection.h
src/cursor.c
src/cursor.h
src/init.c
src/init.h
src/microprotocols.c
src/microprotocols.h
src/module.c
src/module.h
src/prepare_protocol.c
src/prepare_protocol.h
src/row.c
src/row.h
src/statement.c
src/statement.h
src/util.c
src/util.h