Metadata-Version: 2.1
Name: sqlite3_arabic_tokenizer
Version: 0.0.1
Summary: sqlite3_arabic_tokenizer with custom sqlite3
Home-page: https://github.com/GreentechApps/sqlite3_arabic_tokenizer.py
Author: Shahriar Nasim Nafi
Author-email: shahriarnasim.nafi@gmail.com
License: zlib/libpng
Platform: ALL
Classifier: Development Status :: 4 - Beta
Classifier: Intended Audience :: Developers
Classifier: License :: OSI Approved :: zlib/libpng License
Classifier: Operating System :: MacOS :: MacOS X
Classifier: Operating System :: Microsoft :: Windows
Classifier: Operating System :: POSIX
Classifier: Programming Language :: C
Classifier: Programming Language :: Python
Classifier: Topic :: Database :: Database Engines/Servers
Classifier: Topic :: Software Development :: Libraries :: Python Modules
License-File: LICENSE
